{
  "date": "20260414",
  "count": 3,
  "articles": [
    {
      "title": "【观点】南华期货：美伊谈判仍在反复，美元指数高开低走",
      "time": "04月14日 09:23",
      "url": "http://goodsfu.10jqka.com.cn/20260414/c675965559.shtml",
      "site_file": "articles/20260414/【观点】南华期货：美伊谈判仍在反复，美元指数高开低走_e22245ded3.html",
      "updated_at": "2026-04-14T09:25:17.564046+08:00"
    },
    {
      "title": "【观点】南华期货：塑料维持高位震荡",
      "time": "04月14日 09:22",
      "url": "http://goodsfu.10jqka.com.cn/20260414/c675965552.shtml",
      "site_file": "articles/20260414/【观点】南华期货：塑料维持高位震荡_b1ce6d1df1.html",
      "updated_at": "2026-04-14T09:25:17.614317+08:00"
    },
    {
      "title": "【观点】南华期货：碳酸锂利空落地等于利多",
      "time": "04月14日 09:12",
      "url": "http://goodsfu.10jqka.com.cn/20260414/c675964581.shtml",
      "site_file": "articles/20260414/【观点】南华期货：碳酸锂利空落地等于利多_8fdb1dd7cb.html",
      "updated_at": "2026-04-14T09:20:27.185650+08:00"
    }
  ]
}