{
  "date": "20260424",
  "count": 6,
  "articles": [
    {
      "title": "【观点】申银万国：高温少雨支撑橡胶价格，短期震荡上行",
      "time": "04月24日 09:14",
      "url": "http://goodsfu.10jqka.com.cn/20260424/c676244870.shtml",
      "site_file": "articles/20260424/【观点】申银万国：高温少雨支撑橡胶价格，短期震荡上行_871c7d8f16.html",
      "updated_at": "2026-04-24T09:15:20.507657+08:00"
    },
    {
      "title": "【观点】正信期货研究院：锌价窄幅震荡，库存压力依旧不减",
      "time": "04月24日 09:14",
      "url": "http://goodsfu.10jqka.com.cn/20260424/c676244868.shtml",
      "site_file": "articles/20260424/【观点】正信期货研究院：锌价窄幅震荡，库存压力依旧不减_7cb2544a34.html",
      "updated_at": "2026-04-24T09:15:20.548526+08:00"
    },
    {
      "title": "【观点】光大期货：碳酸锂短期供给偏紧，建议关注低多机会",
      "time": "04月24日 09:14",
      "url": "http://goodsfu.10jqka.com.cn/20260424/c676244869.shtml",
      "site_file": "articles/20260424/【观点】光大期货：碳酸锂短期供给偏紧，建议关注低多机会_3fdfce7962.html",
      "updated_at": "2026-04-24T09:15:20.577674+08:00"
    },
    {
      "title": "【观点】国都期货：玉米供给压力有限，上行空间受限",
      "time": "04月24日 09:14",
      "url": "http://goodsfu.10jqka.com.cn/20260424/c676244865.shtml",
      "site_file": "articles/20260424/【观点】国都期货：玉米供给压力有限，上行空间受限_a79d05d76e.html",
      "updated_at": "2026-04-24T09:15:20.591450+08:00"
    },
    {
      "title": "【观点】南华期货：中东地缘担忧升温贵金属偏弱运行",
      "time": "04月24日 09:14",
      "url": "http://goodsfu.10jqka.com.cn/20260424/c676244864.shtml",
      "site_file": "articles/20260424/【观点】南华期货：中东地缘担忧升温贵金属偏弱运行_c01c698ed0.html",
      "updated_at": "2026-04-24T09:15:20.674886+08:00"
    },
    {
      "title": "【观点】国都期货：棉花减产预期兑现，建议调整后做多",
      "time": "04月24日 09:13",
      "url": "http://goodsfu.10jqka.com.cn/20260424/c676244852.shtml",
      "site_file": "articles/20260424/【观点】国都期货：棉花减产预期兑现，建议调整后做多_b02e52c39b.html",
      "updated_at": "2026-04-24T09:15:21.395080+08:00"
    }
  ]
}